[
  {
    "PROPER_NAME": "This is displayed in the tooltip.",
    "NAMES": [
      "these",
      "are",
      "detected",
      "in",
      "the",
      "text"
    ],
    "DESCRIPTION": "This is displayed in the tooltip. Note, spaces are not allowed in NAMES. For multi-word keywords, see the next one."
  },
  {
    "PROPER_NAME": "Multiword Keyword",
    "NAMES": [
      "Multiword Keyword",
      "multiword_keyword",
      "multiword_keywords"
    ],
    "DESCRIPTION": "Make sure the first element in the NAMES is the same as your PROPER_NAME. The rest should use _ to replace spaces. In card text, you'll use the underscore versions."
  },
  {
    "PROPER_NAME": "Banned",
    "NAMES": [
      "Banned",
      "banned"
    ],
    "DESCRIPTION": "Cannot be played."
  },
  {
    "PROPER_NAME": "Limited",
    "NAMES": [
      "Limited",
      "limited"
    ],
    "DESCRIPTION": "You may only use one Limited card each combat. When you play a Limited card all other Limited cards become Banned. (Cannot be played.)"
  },
  {
    "PROPER_NAME": "Entangled",
    "NAMES": [
      "Entangled",
      "entangled"
    ],
    "DESCRIPTION": "Cannot play attacks this turn."
  },{
  "PROPER_NAME": "Status Effect",
  "NAMES": [
    "Status Effect",
    "status_effect",
    "Status_Effect"
  ],
  "DESCRIPTION": "Bosses are Immune to status effects. Status effects have a 25% chance of working on elites."
}
]